LICENSE
NOTICE
README.md
pyproject.toml
lsp/config.yml
switch/__init__.py
switch/api/__init__.py
switch/api/installer.py
switch/api/job_parameters.py
switch/api/job_runner.py
switch/notebooks/00_main.py
switch/notebooks/__init__.py
switch/notebooks/notebook_utils.py
switch/notebooks/validation_utils.py
switch/notebooks/exporters/__init__.py
switch/notebooks/exporters/convert_notebook_to_sql.py
switch/notebooks/exporters/export_to_file.py
switch/notebooks/exporters/export_to_notebook.py
switch/notebooks/external_model/external_model_amazon_bedrock.py
switch/notebooks/external_model/external_model_azure_openai.py
switch/notebooks/external_model/helper_external_model.py
switch/notebooks/orchestrators/__init__.py
switch/notebooks/orchestrators/orchestrate_to_file.py
switch/notebooks/orchestrators/orchestrate_to_notebook.py
switch/notebooks/processors/__init__.py
switch/notebooks/processors/analyze_input_files.py
switch/notebooks/processors/convert_with_llm.py
switch/notebooks/processors/fix_syntax_with_llm.py
switch/notebooks/processors/split_code_into_cells.py
switch/notebooks/processors/validate_python_notebook.py
switch/notebooks/pyscripts/__init__.py
switch/notebooks/pyscripts/helpers/__init__.py
switch/notebooks/pyscripts/helpers/batch_inference_helper.py
switch/notebooks/pyscripts/helpers/cell_split_helper.py
switch/notebooks/pyscripts/helpers/conversion_prompt_helper.py
switch/notebooks/pyscripts/helpers/conversion_result_clean_helper.py
switch/notebooks/pyscripts/helpers/llm_token_count_helper.py
switch/notebooks/pyscripts/helpers/notebook_export_helper.py
switch/notebooks/pyscripts/helpers/spark_sql_extract_helper.py
switch/notebooks/pyscripts/types/__init__.py
switch/notebooks/pyscripts/types/builtin_prompt.py
switch/notebooks/pyscripts/types/comment_language.py
switch/notebooks/pyscripts/types/log_level.py
switch/notebooks/pyscripts/types/notebook_parameters.py
switch/notebooks/pyscripts/types/source_format.py
switch/notebooks/pyscripts/types/table_config.py
databricks_switch_plugin-1.0.2.dist-info/METADATA
databricks_switch_plugin-1.0.2.dist-info/WHEEL
databricks_switch_plugin-1.0.2.dist-info/licenses/LICENSE
databricks_switch_plugin-1.0.2.dist-info/licenses/NOTICE
databricks_switch_plugin-1.0.2.dist-info/RECORD
