Metadata-Version: 2.4
Name: databricks-switch-plugin
Version: 1.0.2
Summary: LLM-powered tool to convert SQL, code, and workflow files into Databricks notebooks.
Project-URL: Documentation, https://databrickslabs.github.io/lakebridge
Project-URL: Issues, https://github.com/databrickslabs/lakebridge/issues
Project-URL: Source, https://github.com/databrickslabs/lakebridge
Maintainer-email: Databricks Labs <labs-oss@databricks.com>
License-File: LICENSE
License-File: NOTICE
Keywords: Conversion,Databricks,LLM,Migration,SQL
Classifier: Development Status :: 4 - Beta
Classifier: Environment :: Console
Classifier: Framework :: Pytest
Classifier: Intended Audience :: Developers
Classifier: Intended Audience :: System Administrators
Classifier: License :: Other/Proprietary License
Classifier: Operating System :: MacOS
Classifier: Operating System :: Microsoft :: Windows
Classifier: Programming Language :: Python
Classifier: Programming Language :: Python :: 3.10
Classifier: Programming Language :: Python :: 3.11
Classifier: Programming Language :: Python :: 3.12
Classifier: Programming Language :: Python :: Implementation :: CPython
Classifier: Topic :: Software Development :: Libraries
Classifier: Topic :: Utilities
Requires-Python: >=3.10
Requires-Dist: anytree==2.13.0
Requires-Dist: chardet==5.2.0
Requires-Dist: httpx==0.28.1
Requires-Dist: omegaconf==2.3.0
Requires-Dist: pyyaml==6.0.2
Requires-Dist: tenacity==9.1.2
Requires-Dist: tiktoken==0.9.0
Provides-Extra: dev
Requires-Dist: black~=25.1.0; extra == 'dev'
Requires-Dist: coverage[toml]~=7.8.0; extra == 'dev'
Requires-Dist: databricks-connect~=17.0.1; extra == 'dev'
Requires-Dist: databricks-labs-pylint~=0.4.0; extra == 'dev'
Requires-Dist: databricks-labs-pytester>=0.3.0; extra == 'dev'
Requires-Dist: databricks-sdk~=0.51.0; extra == 'dev'
Requires-Dist: hatch; extra == 'dev'
Requires-Dist: mypy~=1.10.0; extra == 'dev'
Requires-Dist: pylint-pytest==2.0.0a0; extra == 'dev'
Requires-Dist: pylint~=3.2.2; extra == 'dev'
Requires-Dist: pytest-asyncio~=0.26.0; extra == 'dev'
Requires-Dist: pytest-cov<6.0.0,>=5.0.0; extra == 'dev'
Requires-Dist: pytest-xdist~=3.5.0; extra == 'dev'
Requires-Dist: pytest~=8.3.5; extra == 'dev'
Requires-Dist: python-dotenv>=1.0.0; extra == 'dev'
Requires-Dist: ruff~=0.11.6; extra == 'dev'
Requires-Dist: twine<7.0.0,>=6.0.0; extra == 'dev'
Requires-Dist: types-pytz~=2025.2; extra == 'dev'
Requires-Dist: types-pyyaml~=6.0.12; extra == 'dev'
